teknohole/__init__.py
teknohole/main.py
teknohole/web/__init__.py
teknohole/web/client.py
teknohole-1.0.0.dist-info/licenses/LICENSE
teknohole-1.0.0.dist-info/METADATA
teknohole-1.0.0.dist-info/WHEEL
teknohole-1.0.0.dist-info/entry_points.txt
teknohole-1.0.0.dist-info/top_level.txt
teknohole-1.0.0.dist-info/RECORD
