Metadata-Version: 2.4
Name: teknohole
Version: 1.0.0
Summary: Package CLI resmi dari teknohole.com
Author-email: Teknohole <support@teknohole.com>
Project-URL: Homepage, https://github.com/teknohole/teknoholePIP
Classifier: Programming Language :: Python :: 3
Classifier: License :: OSI Approved :: MIT License
Classifier: Operating System :: OS Independent
Requires-Python: >=3.7
License-File: LICENSE
Requires-Dist: requests
Requires-Dist: rich
Requires-Dist: httpx[http2]
Requires-Dist: tqdm
Dynamic: license-file
